{
    "name": "Pork, fresh, variety meats and by-products, stomach, raw",
    "nutrients": {
        "405": {
            "amount": 0.43778111073325576,
            "source": "USDA"
        },
        "306": {
            "amount": 0.37136034995255196,
            "source": "USDA"
        },
        "320": {
            "amount": 0.0,
            "source": "USDA"
        },
        "517": {
            "amount": 1.0981064827887477,
            "source": "Imputed from USDA"
        },
        "334": {
            "amount": 0.0,
            "source": "USDA"
        },
        "618": {
            "amount": 0.14705873996143412,
            "source": "USDA"
        },
        "619": {
            "amount": 0.018963440177962802,
            "source": "USDA"
        },
        "505": {
            "amount": 1.4268254528013675,
            "source": "Imputed from USDA"
        },
        "630": {
            "amount": 0.0,
            "source": "USDA"
        },
        "503": {
            "amount": 1.4623020434113692,
            "source": "Imputed from USDA"
        },
        "435": {
            "amount": 0.013876737133439603,
            "source": "USDA"
        },
        "578": {
            "amount": 0.0,
            "source": "USDA"
        },
        "515": {
            "amount": 1.4101469603653347,
            "source": "Imputed from USDA"
        },
        "504": {
            "amount": 1.519775125357131,
            "source": "Imputed from USDA"
        },
        "303": {
            "amount": 0.1750718635822641,
            "source": "USDA"
        },
        "509": {
            "amount": 1.4601810952869458,
            "source": "Imputed from USDA"
        },
        "208": {
            "amount": 0.9360539652388843,
            "source": "USDA"
        },
        "605": {
            "amount": 0.06429618324514828,
            "source": "USDA"
        },
        "573": {
            "amount": 0.0,
            "source": "USDA"
        },
        "305": {
            "amount": 0.6318832053085167,
            "source": "USDA"
        },
        "328": {
            "amount": 0.0,
            "source": "USDA"
        },
        "255": {
            "amount": 2.3887419348118444,
            "source": "USDA"
        },
        "609": {
            "amount": 0.0,
            "source": "USDA"
        },
        "204": {
            "amount": 0.6336764703853262,
            "source": "USDA"
        },
        "620": {
            "amount": 1.2554783027495529,
            "source": "USDA"
        },
        "321": {
            "amount": 0.0,
            "source": "USDA"
        },
        "612": {
            "amount": 0.073566084150427,
            "source": "USDA"
        },
        "631": {
            "amount": 0.0,
            "source": "USDA"
        },
        "415": {
            "amount": 0.06906011865454169,
            "source": "USDA"
        },
        "404": {
            "amount": 0.09514053717807593,
            "source": "USDA"
        },
        "205": {
            "amount": 0.0,
            "source": "USDA"
        },
        "645": {
            "amount": 0.5047349434533208,
            "source": "USDA"
        },
        "516": {
            "amount": 1.0736815475738997,
            "source": "Imputed from USDA"
        },
        "315": {
            "amount": 0.005183223820696505,
            "source": "USDA"
        },
        "501": {
            "amount": 1.3207730953142502,
            "source": "Imputed from USDA"
        },
        "421": {
            "amount": 3.058535128206457,
            "source": "USDA"
        },
        "430": {
            "amount": 0.0,
            "source": "USDA"
        },
        "323": {
            "amount": 0.008385159562855704,
            "source": "USDA"
        },
        "207": {
            "amount": 0.20863771341262374,
            "source": "USDA"
        },
        "318": {
            "amount": 0.0,
            "source": "USDA"
        },
        "514": {
            "amount": 1.4015988126336847,
            "source": "Imputed from USDA"
        },
        "406": {
            "amount": 0.5076910116670581,
            "source": "USDA"
        },
        "614": {
            "amount": 0.6881163781908582,
            "source": "USDA"
        },
        "268": {
            "amount": 0.9355992385405215,
            "source": "USDA"
        },
        "417": {
            "amount": 0.02115927435270893,
            "source": "USDA"
        },
        "291": {
            "amount": 0.0,
            "source": "USDA"
        },
        "511": {
            "amount": 1.3208354965188907,
            "source": "Imputed from USDA"
        },
        "203": {
            "amount": 1.6000985090376332,
            "source": "USDA"
        },
        "432": {
            "amount": 0.04566225701259982,
            "source": "USDA"
        },
        "410": {
            "amount": 0.8503975187400074,
            "source": "USDA"
        },
        "418": {
            "amount": 0.05299725191388051,
            "source": "USDA"
        },
        "507": {
            "amount": 1.1582599856913987,
            "source": "Imputed from USDA"
        },
        "322": {
            "amount": 0.0,
            "source": "USDA"
        },
        "431": {
            "amount": 0.0,
            "source": "USDA"
        },
        "269": {
            "amount": 0.0,
            "source": "USDA"
        },
        "613": {
            "amount": 0.7886883566888054,
            "source": "USDA"
        },
        "512": {
            "amount": 1.282871568231374,
            "source": "Imputed from USDA"
        },
        "626": {
            "amount": 0.3034358141621325,
            "source": "USDA"
        },
        "606": {
            "amount": 0.6063558818016059,
            "source": "USDA"
        },
        "610": {
            "amount": 0.0,
            "source": "USDA"
        },
        "304": {
            "amount": 0.18988562896510064,
            "source": "USDA"
        },
        "338": {
            "amount": 0.0,
            "source": "USDA"
        },
        "510": {
            "amount": 1.4726908304575903,
            "source": "Imputed from USDA"
        },
        "607": {
            "amount": 0.0,
            "source": "USDA"
        },
        "337": {
            "amount": 0.0,
            "source": "USDA"
        },
        "608": {
            "amount": 0.0,
            "source": "USDA"
        },
        "628": {
            "amount": 0.13981156769281444,
            "source": "USDA"
        },
        "646": {
            "amount": 0.16825137615346286,
            "source": "USDA"
        },
        "221": {
            "amount": 0.0,
            "source": "USDA"
        },
        "601": {
            "amount": 1.4615532323115892,
            "source": "USDA"
        },
        "319": {
            "amount": 0.0,
            "source": "USDA"
        },
        "502": {
            "amount": 1.5240734234112927,
            "source": "Imputed from USDA"
        },
        "312": {
            "amount": 0.28616184448845267,
            "source": "USDA"
        },
        "317": {
            "amount": 1.000011887106226,
            "source": "USDA"
        },
        "324": {
            "amount": 0.0,
            "source": "USDA"
        },
        "621": {
            "amount": 0.0,
            "source": "USDA"
        },
        "401": {
            "amount": 0.0,
            "source": "USDA"
        },
        "518": {
            "amount": 1.4535333708731177,
            "source": "Imputed from USDA"
        },
        "513": {
            "amount": 1.4054143185043477,
            "source": "Imputed from USDA"
        },
        "617": {
            "amount": 0.47244862946116467,
            "source": "USDA"
        },
        "506": {
            "amount": 1.4124787688739366,
            "source": "Imputed from USDA"
        },
        "508": {
            "amount": 1.450557476887579,
            "source": "Imputed from USDA"
        },
        "263": {
            "amount": 0.0,
            "source": "USDA"
        },
        "611": {
            "amount": 0.0,
            "source": "USDA"
        },
        "627": {
            "amount": 0.0,
            "source": "USDA"
        },
        "629": {
            "amount": 0.0,
            "source": "USDA"
        },
        "307": {
            "amount": 0.07867949900376044,
            "source": "USDA"
        },
        "301": {
            "amount": 0.053316750865333766,
            "source": "USDA"
        },
        "262": {
            "amount": 0.0,
            "source": "USDA"
        },
        "309": {
            "amount": 0.53583718492967,
            "source": "USDA"
        }
    },
    "id": "USDA_10119"
}

