{
    "name": "Celery, cooked, boiled, drained, without salt",
    "nutrients": {
        "405": {
            "amount": 0.15246108333993982,
            "source": "USDA"
        },
        "306": {
            "amount": 0.7533309956180341,
            "source": "USDA"
        },
        "320": {
            "amount": 0.02496076802242544,
            "source": "USDA"
        },
        "517": {
            "amount": 0.03627483042002769,
            "source": "USDA"
        },
        "334": {
            "amount": 0.0,
            "source": "USDA"
        },
        "618": {
            "amount": 0.015233985493242485,
            "source": "USDA"
        },
        "619": {
            "amount": 0.0,
            "source": "USDA"
        },
        "505": {
            "amount": 0.03244756621976505,
            "source": "USDA"
        },
        "630": {
            "amount": 0.0,
            "source": "USDA"
        },
        "503": {
            "amount": 0.04846252827968404,
            "source": "USDA"
        },
        "435": {
            "amount": 0.15264410846783563,
            "source": "USDA"
        },
        "578": {
            "amount": 0.0,
            "source": "USDA"
        },
        "515": {
            "amount": 0.06129960642092871,
            "source": "USDA"
        },
        "504": {
            "amount": 0.043885857831455974,
            "source": "USDA"
        },
        "303": {
            "amount": 0.07280216109361476,
            "source": "USDA"
        },
        "509": {
            "amount": 0.027909980081983442,
            "source": "USDA"
        },
        "208": {
            "amount": 0.10596837342326992,
            "source": "USDA"
        },
        "605": {
            "amount": 0.0,
            "source": "USDA"
        },
        "573": {
            "amount": 0.0,
            "source": "USDA"
        },
        "305": {
            "amount": 0.12151600102086861,
            "source": "USDA"
        },
        "328": {
            "amount": 0.0,
            "source": "USDA"
        },
        "255": {
            "amount": 3.058564673267247,
            "source": "USDA"
        },
        "609": {
            "amount": 0.0,
            "source": "USDA"
        },
        "204": {
            "amount": 0.009998839769393706,
            "source": "USDA"
        },
        "620": {
            "amount": 0.0,
            "source": "USDA"
        },
        "321": {
            "amount": 0.1637476324726151,
            "source": "USDA"
        },
        "612": {
            "amount": 0.000588528673203416,
            "source": "USDA"
        },
        "631": {
            "amount": 0.0,
            "source": "USDA"
        },
        "415": {
            "amount": 0.1746814765967819,
            "source": "USDA"
        },
        "404": {
            "amount": 0.04290651676658326,
            "source": "USDA"
        },
        "205": {
            "amount": 0.1437484916609827,
            "source": "USDA"
        },
        "645": {
            "amount": 0.004217840753091817,
            "source": "USDA"
        },
        "516": {
            "amount": 0.035152213442554286,
            "source": "USDA"
        },
        "315": {
            "amount": 0.014458466447206041,
            "source": "USDA"
        },
        "501": {
            "amount": 0.08523363982473908,
            "source": "USDA"
        },
        "421": {
            "amount": 0.1240371022219251,
            "source": "USDA"
        },
        "430": {
            "amount": 0.4227483650605769,
            "source": "USDA"
        },
        "323": {
            "amount": 0.07337014617498741,
            "source": "USDA"
        },
        "207": {
            "amount": 0.29805387630374824,
            "source": "USDA"
        },
        "318": {
            "amount": 0.11596442862470593,
            "source": "USDA"
        },
        "514": {
            "amount": 0.13296066705044526,
            "source": "USDA"
        },
        "406": {
            "amount": 0.07615365175005873,
            "source": "USDA"
        },
        "614": {
            "amount": 0.0017300223210329562,
            "source": "USDA"
        },
        "268": {
            "amount": 0.10411179496541141,
            "source": "USDA"
        },
        "417": {
            "amount": 0.23275201787979824,
            "source": "USDA"
        },
        "291": {
            "amount": 0.3066984180142847,
            "source": "USDA"
        },
        "511": {
            "amount": 0.029973203839165023,
            "source": "USDA"
        },
        "203": {
            "amount": 0.07881790875378251,
            "source": "USDA"
        },
        "432": {
            "amount": 0.502284827138598,
            "source": "USDA"
        },
        "410": {
            "amount": 0.22096394544310027,
            "source": "USDA"
        },
        "418": {
            "amount": 0.0,
            "source": "USDA"
        },
        "507": {
            "amount": 0.03522961308773198,
            "source": "USDA"
        },
        "322": {
            "amount": 0.0,
            "source": "USDA"
        },
        "431": {
            "amount": 0.0,
            "source": "USDA"
        },
        "269": {
            "amount": 0.1430235082173324,
            "source": "USDA"
        },
        "613": {
            "amount": 0.012192620355171465,
            "source": "USDA"
        },
        "512": {
            "amount": 0.03728094820781299,
            "source": "USDA"
        },
        "626": {
            "amount": 0.001502157495852141,
            "source": "USDA"
        },
        "606": {
            "amount": 0.006025896962003537,
            "source": "USDA"
        },
        "610": {
            "amount": 0.0,
            "source": "USDA"
        },
        "304": {
            "amount": 0.20714795887101886,
            "source": "USDA"
        },
        "338": {
            "amount": 0.18500677857246686,
            "source": "USDA"
        },
        "510": {
            "amount": 0.058764842596610904,
            "source": "USDA"
        },
        "607": {
            "amount": 0.0,
            "source": "USDA"
        },
        "337": {
            "amount": 0.0,
            "source": "USDA"
        },
        "608": {
            "amount": 0.0,
            "source": "USDA"
        },
        "628": {
            "amount": 0.0,
            "source": "USDA"
        },
        "646": {
            "amount": 0.014146696425459319,
            "source": "USDA"
        },
        "221": {
            "amount": 0.0,
            "source": "USDA"
        },
        "601": {
            "amount": 0.0,
            "source": "USDA"
        },
        "319": {
            "amount": 0.0,
            "source": "USDA"
        },
        "502": {
            "amount": 0.05014209071481542,
            "source": "USDA"
        },
        "312": {
            "amount": 0.06095755267209642,
            "source": "USDA"
        },
        "317": {
            "amount": 0.032154723058078004,
            "source": "USDA"
        },
        "324": {
            "amount": 0.0,
            "source": "USDA"
        },
        "621": {
            "amount": 0.0,
            "source": "USDA"
        },
        "401": {
            "amount": 0.062383574748957706,
            "source": "USDA"
        },
        "518": {
            "amount": 0.050615084177447825,
            "source": "USDA"
        },
        "513": {
            "amount": 0.04010299528302271,
            "source": "USDA"
        },
        "617": {
            "amount": 0.004126810317582463,
            "source": "USDA"
        },
        "506": {
            "amount": 0.022928926423957847,
            "source": "USDA"
        },
        "508": {
            "amount": 0.05168809931997762,
            "source": "USDA"
        },
        "263": {
            "amount": 0.0,
            "source": "USDA"
        },
        "611": {
            "amount": 0.0,
            "source": "USDA"
        },
        "627": {
            "amount": 0.0,
            "source": "USDA"
        },
        "629": {
            "amount": 0.0,
            "source": "USDA"
        },
        "307": {
            "amount": 0.09546445879122933,
            "source": "USDA"
        },
        "301": {
            "amount": 0.2035730487585471,
            "source": "USDA"
        },
        "262": {
            "amount": 0.0,
            "source": "USDA"
        },
        "309": {
            "amount": 0.04054984102170476,
            "source": "USDA"
        }
    },
    "id": "USDA_11144"
}

