{
    "name": "Cookies, vanilla wafers, lower fat",
    "nutrients": {
        "405": {
            "amount": 0.6969649524111534,
            "source": "USDA"
        },
        "306": {
            "amount": 0.2572996710385539,
            "source": "USDA"
        },
        "320": {
            "amount": 0.007680236314592443,
            "source": "USDA"
        },
        "517": {
            "amount": 0.7320920321132861,
            "source": "USDA"
        },
        "334": {
            "amount": 0.002503763855290369,
            "source": "USDA"
        },
        "618": {
            "amount": 0.7363092988400535,
            "source": "USDA"
        },
        "619": {
            "amount": 0.20859784195759082,
            "source": "USDA"
        },
        "505": {
            "amount": 0.23321688220456133,
            "source": "USDA"
        },
        "630": {
            "amount": 0.0,
            "source": "USDA"
        },
        "503": {
            "amount": 0.412900740942908,
            "source": "USDA"
        },
        "435": {
            "amount": 0.4440555882700673,
            "source": "USDA"
        },
        "578": {
            "amount": 0.0,
            "source": "USDA"
        },
        "515": {
            "amount": 0.7648128464667273,
            "source": "USDA"
        },
        "504": {
            "amount": 0.4107266181661905,
            "source": "USDA"
        },
        "303": {
            "amount": 0.41254557953048365,
            "source": "USDA"
        },
        "509": {
            "amount": 0.40596334664703193,
            "source": "USDA"
        },
        "208": {
            "amount": 2.596225148870113,
            "source": "USDA"
        },
        "605": {
            "amount": 0.13991973432700947,
            "source": "Imputed from USDA"
        },
        "573": {
            "amount": 0.0,
            "source": "USDA"
        },
        "305": {
            "amount": 0.5055065642468134,
            "source": "USDA"
        },
        "328": {
            "amount": 0.0,
            "source": "USDA"
        },
        "255": {
            "amount": 0.16574944037469938,
            "source": "USDA"
        },
        "609": {
            "amount": 0.0,
            "source": "USDA"
        },
        "204": {
            "amount": 0.949889778092402,
            "source": "USDA"
        },
        "620": {
            "amount": 0.19402846497038545,
            "source": "USDA"
        },
        "321": {
            "amount": 0.0005231553753118693,
            "source": "USDA"
        },
        "612": {
            "amount": 0.035311720392204954,
            "source": "USDA"
        },
        "631": {
            "amount": 0.0,
            "source": "USDA"
        },
        "415": {
            "amount": 0.14827613711122184,
            "source": "USDA"
        },
        "404": {
            "amount": 0.5130127004700173,
            "source": "USDA"
        },
        "205": {
            "amount": 2.644972246562081,
            "source": "USDA"
        },
        "645": {
            "amount": 0.920051662941095,
            "source": "USDA"
        },
        "516": {
            "amount": 0.22578537095794488,
            "source": "USDA"
        },
        "315": {
            "amount": 0.035736964237433805,
            "source": "USDA"
        },
        "501": {
            "amount": 0.5268988643711144,
            "source": "USDA"
        },
        "421": {
            "amount": 0.43334481282596615,
            "source": "USDA"
        },
        "430": {
            "amount": 0.06710291508898046,
            "source": "USDA"
        },
        "323": {
            "amount": 0.0482146674864203,
            "source": "USDA"
        },
        "207": {
            "amount": 0.3642880710379145,
            "source": "USDA"
        },
        "318": {
            "amount": 0.006677414316201877,
            "source": "USDA"
        },
        "514": {
            "amount": 0.28006608591476767,
            "source": "USDA"
        },
        "406": {
            "amount": 0.6358420492894687,
            "source": "USDA"
        },
        "614": {
            "amount": 0.6673561103384628,
            "source": "USDA"
        },
        "268": {
            "amount": 2.5957602933943793,
            "source": "USDA"
        },
        "417": {
            "amount": 0.42318548705417863,
            "source": "USDA"
        },
        "291": {
            "amount": 0.3642043713919631,
            "source": "USDA"
        },
        "511": {
            "amount": 0.2760032520189779,
            "source": "USDA"
        },
        "203": {
            "amount": 0.4748066792396537,
            "source": "USDA"
        },
        "432": {
            "amount": 0.13698677103779947,
            "source": "USDA"
        },
        "410": {
            "amount": 0.2857893300683631,
            "source": "USDA"
        },
        "418": {
            "amount": 0.02296547582934822,
            "source": "USDA"
        },
        "507": {
            "amount": 0.7750514879301035,
            "source": "USDA"
        },
        "322": {
            "amount": 0.0,
            "source": "USDA"
        },
        "431": {
            "amount": 0.20721857619942285,
            "source": "USDA"
        },
        "269": {
            "amount": 2.2630301933122214,
            "source": "USDA"
        },
        "613": {
            "amount": 0.7817211450572791,
            "source": "USDA"
        },
        "512": {
            "amount": 0.282270036430584,
            "source": "USDA"
        },
        "626": {
            "amount": 0.046566882371416374,
            "source": "USDA"
        },
        "606": {
            "amount": 0.5781848135042393,
            "source": "USDA"
        },
        "610": {
            "amount": 0.0,
            "source": "USDA"
        },
        "304": {
            "amount": 0.24167261868285536,
            "source": "USDA"
        },
        "338": {
            "amount": 0.023055555992313497,
            "source": "USDA"
        },
        "510": {
            "amount": 0.43450368465372907,
            "source": "USDA"
        },
        "607": {
            "amount": 0.0,
            "source": "USDA"
        },
        "337": {
            "amount": 0.0,
            "source": "USDA"
        },
        "608": {
            "amount": 0.0,
            "source": "USDA"
        },
        "628": {
            "amount": 0.006168157398212401,
            "source": "USDA"
        },
        "646": {
            "amount": 0.733176120076805,
            "source": "USDA"
        },
        "221": {
            "amount": 0.0,
            "source": "USDA"
        },
        "601": {
            "amount": 0.33425656882462357,
            "source": "USDA"
        },
        "319": {
            "amount": 0.006264012391727707,
            "source": "USDA"
        },
        "502": {
            "amount": 0.35308388878349195,
            "source": "USDA"
        },
        "312": {
            "amount": 0.16932653520026783,
            "source": "USDA"
        },
        "317": {
            "amount": 0.36334837055628144,
            "source": "USDA"
        },
        "324": {
            "amount": 0.0,
            "source": "USDA"
        },
        "621": {
            "amount": 0.006570308719078111,
            "source": "USDA"
        },
        "401": {
            "amount": 0.0,
            "source": "USDA"
        },
        "518": {
            "amount": 0.6179258193330088,
            "source": "USDA"
        },
        "513": {
            "amount": 0.2792356708595655,
            "source": "USDA"
        },
        "617": {
            "amount": 0.9261131567871265,
            "source": "USDA"
        },
        "506": {
            "amount": 0.34393389635936766,
            "source": "USDA"
        },
        "508": {
            "amount": 0.5233420056147734,
            "source": "USDA"
        },
        "263": {
            "amount": 0.0,
            "source": "USDA"
        },
        "611": {
            "amount": 0.0,
            "source": "USDA"
        },
        "627": {
            "amount": 0.008130400020216935,
            "source": "USDA"
        },
        "629": {
            "amount": 0.012641455608908466,
            "source": "USDA"
        },
        "307": {
            "amount": 0.4070352748461207,
            "source": "USDA"
        },
        "301": {
            "amount": 0.23265491286691098,
            "source": "USDA"
        },
        "262": {
            "amount": 0.0,
            "source": "USDA"
        },
        "309": {
            "amount": 0.10427101977009794,
            "source": "USDA"
        }
    },
    "id": "USDA_18212"
}

