{
    "name": "Beef, ground, 90% lean meat / 10% fat, loaf, cooked, baked",
    "nutrients": {
        "405": {
            "amount": 0.37244064644471014,
            "source": "USDA"
        },
        "306": {
            "amount": 0.7957721784697542,
            "source": "USDA"
        },
        "320": {
            "amount": 0.0028800886179721663,
            "source": "USDA"
        },
        "517": {
            "amount": 2.235848638616252,
            "source": "USDA"
        },
        "334": {
            "amount": 0.0,
            "source": "USDA"
        },
        "618": {
            "amount": 0.05727978545459174,
            "source": "USDA"
        },
        "619": {
            "amount": 0.008127188647698342,
            "source": "USDA"
        },
        "505": {
            "amount": 2.234826123386318,
            "source": "USDA"
        },
        "630": {
            "amount": 0.0,
            "source": "USDA"
        },
        "503": {
            "amount": 2.279677330276337,
            "source": "USDA"
        },
        "435": {
            "amount": 0.027753474266879206,
            "source": "USDA"
        },
        "578": {
            "amount": 0.0,
            "source": "USDA"
        },
        "515": {
            "amount": 2.2852722431129404,
            "source": "USDA"
        },
        "504": {
            "amount": 2.334952692314645,
            "source": "USDA"
        },
        "303": {
            "amount": 0.5009482037155873,
            "source": "USDA"
        },
        "509": {
            "amount": 2.0754876097329507,
            "source": "USDA"
        },
        "208": {
            "amount": 1.2598462173655423,
            "source": "USDA"
        },
        "605": {
            "amount": 0.1844805873110793,
            "source": "USDA"
        },
        "573": {
            "amount": 0.0,
            "source": "USDA"
        },
        "305": {
            "amount": 0.9381035278811056,
            "source": "USDA"
        },
        "328": {
            "amount": 0.0,
            "source": "USDA"
        },
        "255": {
            "amount": 1.993218270231434,
            "source": "USDA"
        },
        "609": {
            "amount": 0.0,
            "source": "USDA"
        },
        "204": {
            "amount": 0.6936695090016883,
            "source": "USDA"
        },
        "620": {
            "amount": 0.4679510037521061,
            "source": "USDA"
        },
        "321": {
            "amount": 0.0,
            "source": "USDA"
        },
        "612": {
            "amount": 0.1877406467518897,
            "source": "USDA"
        },
        "631": {
            "amount": 0.0,
            "source": "USDA"
        },
        "415": {
            "amount": 0.7048194462684108,
            "source": "USDA"
        },
        "404": {
            "amount": 0.0690235269723296,
            "source": "USDA"
        },
        "205": {
            "amount": 0.0,
            "source": "USDA"
        },
        "645": {
            "amount": 0.6568583999481656,
            "source": "USDA"
        },
        "516": {
            "amount": 2.4417268260481944,
            "source": "USDA"
        },
        "315": {
            "amount": 0.0013640062686043437,
            "source": "USDA"
        },
        "501": {
            "amount": 1.046049216030889,
            "source": "USDA"
        },
        "421": {
            "amount": 1.342426865819569,
            "source": "USDA"
        },
        "430": {
            "amount": 0.01230220109964642,
            "source": "USDA"
        },
        "323": {
            "amount": 0.02515547868856711,
            "source": "USDA"
        },
        "207": {
            "amount": 0.30798900551387315,
            "source": "USDA"
        },
        "318": {
            "amount": 0.002003224294860563,
            "source": "USDA"
        },
        "514": {
            "amount": 2.2593883564033113,
            "source": "USDA"
        },
        "406": {
            "amount": 1.0702454068529759,
            "source": "USDA"
        },
        "614": {
            "amount": 0.6202130020903147,
            "source": "USDA"
        },
        "268": {
            "amount": 1.2577830364740243,
            "source": "USDA"
        },
        "417": {
            "amount": 0.04231854870541786,
            "source": "USDA"
        },
        "291": {
            "amount": 0.0,
            "source": "USDA"
        },
        "511": {
            "amount": 2.1630662103930756,
            "source": "USDA"
        },
        "203": {
            "amount": 2.5278707602719166,
            "source": "USDA"
        },
        "432": {
            "amount": 0.09132451402519964,
            "source": "USDA"
        },
        "410": {
            "amount": 0.4363515137141349,
            "source": "USDA"
        },
        "418": {
            "amount": 0.43987719088520827,
            "source": "USDA"
        },
        "507": {
            "amount": 1.9305827972077125,
            "source": "USDA"
        },
        "322": {
            "amount": 0.0,
            "source": "USDA"
        },
        "431": {
            "amount": 0.0,
            "source": "USDA"
        },
        "269": {
            "amount": 0.0,
            "source": "USDA"
        },
        "613": {
            "amount": 0.8440776891594416,
            "source": "USDA"
        },
        "512": {
            "amount": 2.3007670893964587,
            "source": "USDA"
        },
        "626": {
            "amount": 0.5873435808781872,
            "source": "USDA"
        },
        "606": {
            "amount": 0.6590824802191368,
            "source": "USDA"
        },
        "610": {
            "amount": 0.0,
            "source": "USDA"
        },
        "304": {
            "amount": 0.36250892802428303,
            "source": "USDA"
        },
        "338": {
            "amount": 0.0,
            "source": "USDA"
        },
        "510": {
            "amount": 2.327443917386983,
            "source": "USDA"
        },
        "607": {
            "amount": 0.0,
            "source": "USDA"
        },
        "337": {
            "amount": 0.0,
            "source": "USDA"
        },
        "608": {
            "amount": 0.0,
            "source": "USDA"
        },
        "628": {
            "amount": 0.0781299937106904,
            "source": "USDA"
        },
        "646": {
            "amount": 0.07507180236443746,
            "source": "USDA"
        },
        "221": {
            "amount": 0.0,
            "source": "USDA"
        },
        "601": {
            "amount": 0.5767564324817034,
            "source": "USDA"
        },
        "319": {
            "amount": 0.0023490046468978903,
            "source": "USDA"
        },
        "502": {
            "amount": 2.1519313931774953,
            "source": "USDA"
        },
        "312": {
            "amount": 0.1337679628082116,
            "source": "USDA"
        },
        "317": {
            "amount": 0.6945420180544849,
            "source": "USDA"
        },
        "324": {
            "amount": 0.008474760704113602,
            "source": "USDA"
        },
        "621": {
            "amount": 0.0,
            "source": "USDA"
        },
        "401": {
            "amount": 0.0,
            "source": "USDA"
        },
        "518": {
            "amount": 2.2460443603742473,
            "source": "USDA"
        },
        "513": {
            "amount": 2.4745033385746606,
            "source": "USDA"
        },
        "617": {
            "amount": 0.05307931891235374,
            "source": "USDA"
        },
        "506": {
            "amount": 2.2404836677124527,
            "source": "USDA"
        },
        "508": {
            "amount": 2.235510295589032,
            "source": "USDA"
        },
        "263": {
            "amount": 0.0,
            "source": "USDA"
        },
        "611": {
            "amount": 0.0025135152822435064,
            "source": "USDA"
        },
        "627": {
            "amount": 0.0,
            "source": "USDA"
        },
        "629": {
            "amount": 0.0,
            "source": "USDA"
        },
        "307": {
            "amount": 0.06399265918972516,
            "source": "USDA"
        },
        "301": {
            "amount": 0.06301070556812172,
            "source": "USDA"
        },
        "262": {
            "amount": 0.0,
            "source": "USDA"
        },
        "309": {
            "amount": 1.926117448530976,
            "source": "USDA"
        }
    },
    "id": "USDA_23566"
}

