{
    "name": "Cabbage, raw",
    "nutrients": {
        "405": {
            "amount": 0.08712061905139418,
            "source": "USDA"
        },
        "306": {
            "amount": 0.45093756779952743,
            "source": "USDA"
        },
        "320": {
            "amount": 0.004800147696620277,
            "source": "USDA"
        },
        "517": {
            "amount": 0.07914508455278768,
            "source": "USDA"
        },
        "334": {
            "amount": 0.0,
            "source": "USDA"
        },
        "618": {
            "amount": 0.0034530367118016303,
            "source": "USDA"
        },
        "619": {
            "amount": 0.0,
            "source": "USDA"
        },
        "505": {
            "amount": 0.04461540355217694,
            "source": "USDA"
        },
        "630": {
            "amount": 0.0,
            "source": "USDA"
        },
        "503": {
            "amount": 0.05815503393562084,
            "source": "USDA"
        },
        "435": {
            "amount": 0.19889989891263432,
            "source": "USDA"
        },
        "578": {
            "amount": 0.0,
            "source": "USDA"
        },
        "515": {
            "amount": 0.16843069427806578,
            "source": "USDA"
        },
        "504": {
            "amount": 0.04613641464332551,
            "source": "USDA"
        },
        "303": {
            "amount": 0.08146908503333081,
            "source": "USDA"
        },
        "509": {
            "amount": 0.04820814741433504,
            "source": "USDA"
        },
        "208": {
            "amount": 0.14717829642120822,
            "source": "USDA"
        },
        "605": {
            "amount": 0.0,
            "source": "USDA"
        },
        "573": {
            "amount": 0.0,
            "source": "USDA"
        },
        "305": {
            "amount": 0.12637664106170335,
            "source": "USDA"
        },
        "328": {
            "amount": 0.0,
            "source": "USDA"
        },
        "255": {
            "amount": 2.995839885047018,
            "source": "USDA"
        },
        "609": {
            "amount": 0.0,
            "source": "USDA"
        },
        "204": {
            "amount": 0.006249274855871067,
            "source": "USDA"
        },
        "620": {
            "amount": 0.0,
            "source": "USDA"
        },
        "321": {
            "amount": 0.02197252576309851,
            "source": "USDA"
        },
        "612": {
            "amount": 0.0,
            "source": "USDA"
        },
        "631": {
            "amount": 0.0,
            "source": "USDA"
        },
        "415": {
            "amount": 0.2518663150930344,
            "source": "USDA"
        },
        "404": {
            "amount": 0.11379554446789474,
            "source": "USDA"
        },
        "205": {
            "amount": 0.20843531290842487,
            "source": "USDA"
        },
        "645": {
            "amount": 0.002390109760085363,
            "source": "USDA"
        },
        "516": {
            "amount": 0.040560246279870336,
            "source": "USDA"
        },
        "315": {
            "amount": 0.0218241002976695,
            "source": "USDA"
        },
        "501": {
            "amount": 0.08523363982473908,
            "source": "USDA"
        },
        "421": {
            "amount": 0.16799961946513903,
            "source": "USDA"
        },
        "430": {
            "amount": 0.8499702577937526,
            "source": "USDA"
        },
        "323": {
            "amount": 0.03144434836070889,
            "source": "USDA"
        },
        "207": {
            "amount": 0.21194942314933207,
            "source": "USDA"
        },
        "318": {
            "amount": 0.021812886766259466,
            "source": "USDA"
        },
        "514": {
            "amount": 0.1150439814195342,
            "source": "USDA"
        },
        "406": {
            "amount": 0.047903103520198234,
            "source": "USDA"
        },
        "614": {
            "amount": 0.0,
            "source": "USDA"
        },
        "268": {
            "amount": 0.14491236326266724,
            "source": "USDA"
        },
        "417": {
            "amount": 0.303282932388828,
            "source": "USDA"
        },
        "291": {
            "amount": 0.4792162781473199,
            "source": "USDA"
        },
        "511": {
            "amount": 0.09366626199739068,
            "source": "USDA"
        },
        "203": {
            "amount": 0.12155050988535135,
            "source": "USDA"
        },
        "432": {
            "amount": 0.6544923505139307,
            "source": "USDA"
        },
        "410": {
            "amount": 0.14777399505973898,
            "source": "USDA"
        },
        "418": {
            "amount": 0.0,
            "source": "USDA"
        },
        "507": {
            "amount": 0.07750514879301035,
            "source": "USDA"
        },
        "322": {
            "amount": 0.039960525627243025,
            "source": "USDA"
        },
        "431": {
            "amount": 0.0,
            "source": "USDA"
        },
        "269": {
            "amount": 0.19311190982930956,
            "source": "USDA"
        },
        "613": {
            "amount": 0.011844259773595137,
            "source": "USDA"
        },
        "512": {
            "amount": 0.05858434718370612,
            "source": "USDA"
        },
        "626": {
            "amount": 0.0,
            "source": "USDA"
        },
        "606": {
            "amount": 0.005122012417703006,
            "source": "USDA"
        },
        "610": {
            "amount": 0.0,
            "source": "USDA"
        },
        "304": {
            "amount": 0.20714795887101886,
            "source": "USDA"
        },
        "338": {
            "amount": 0.016869919018765975,
            "source": "USDA"
        },
        "510": {
            "amount": 0.07479161785023206,
            "source": "USDA"
        },
        "607": {
            "amount": 0.0,
            "source": "USDA"
        },
        "337": {
            "amount": 0.0,
            "source": "USDA"
        },
        "608": {
            "amount": 0.0,
            "source": "USDA"
        },
        "628": {
            "amount": 0.0,
            "source": "USDA"
        },
        "646": {
            "amount": 0.0032065845231041127,
            "source": "USDA"
        },
        "221": {
            "amount": 0.0,
            "source": "USDA"
        },
        "601": {
            "amount": 0.0,
            "source": "USDA"
        },
        "319": {
            "amount": 0.0,
            "source": "USDA"
        },
        "502": {
            "amount": 0.07312388229243916,
            "source": "USDA"
        },
        "312": {
            "amount": 0.032172041688050886,
            "source": "USDA"
        },
        "317": {
            "amount": 0.0096464169174234,
            "source": "USDA"
        },
        "324": {
            "amount": 0.0,
            "source": "USDA"
        },
        "621": {
            "amount": 0.0,
            "source": "USDA"
        },
        "401": {
            "amount": 0.37430144849374625,
            "source": "USDA"
        },
        "518": {
            "amount": 0.11177497755853061,
            "source": "USDA"
        },
        "513": {
            "amount": 0.06238243710692422,
            "source": "USDA"
        },
        "617": {
            "amount": 0.002419164668927651,
            "source": "USDA"
        },
        "506": {
            "amount": 0.039306731012499166,
            "source": "USDA"
        },
        "508": {
            "amount": 0.06891746575997015,
            "source": "USDA"
        },
        "263": {
            "amount": 0.0,
            "source": "USDA"
        },
        "611": {
            "amount": 0.0,
            "source": "USDA"
        },
        "627": {
            "amount": 0.0,
            "source": "USDA"
        },
        "629": {
            "amount": 0.0,
            "source": "USDA"
        },
        "307": {
            "amount": 0.018883079760902505,
            "source": "USDA"
        },
        "301": {
            "amount": 0.19387909405575915,
            "source": "USDA"
        },
        "262": {
            "amount": 0.0,
            "source": "USDA"
        },
        "309": {
            "amount": 0.05213550988504897,
            "source": "USDA"
        }
    },
    "id": "USDA_11109"
}

